CHANGELOG.rst
LICENSE
README.rst
js_routes/__init__.py
js_routes/_scripts/__init__.py
js_routes/_scripts/build_static_resolver.py
js_routes/apps.py
js_routes/conf/__init__.py
js_routes/conf/settings.py
js_routes/management/__init__.py
js_routes/management/commands/__init__.py
js_routes/management/commands/dump_routes_resolver.py
js_routes/serializers.py
js_routes/static/js/routes/resolver.js
js_routes/templates/js_routes/_base/resolver.js
js_routes/templates/js_routes/_base/static_resolver.js
js_routes/templates/js_routes/_dump/default.js
js_routes/templates/js_routes/_dump/es6.js
js_routes/templates/js_routes/routes.html
js_routes/templatetags/__init__.py
js_routes/templatetags/js_routes_tags.py
js_routes/test/__init__.py
js_routes/test/utils.py
js_routes/utils/__init__.py
js_routes/utils/text.py
django_js_routes-0.1.4.dist-info/LICENSE
django_js_routes-0.1.4.dist-info/WHEEL
django_js_routes-0.1.4.dist-info/METADATA
django_js_routes-0.1.4.dist-info/RECORD
