Metadata-Version: 2.1
Name: django-js-routes
Version: 0.1.4
Summary: Expose and perform reverse lookups of Django URLs in the frontend world.
Home-page: https://github.com/ellmetha/django-js-routes
License: MIT
Keywords: django,urls,reverse,javascript,export
Author: Morgan Aubert
Author-email: me@morganaubert.name
Requires-Python: >=3.5,<4.0
Classifier: Development Status :: 4 - Beta
Classifier: Environment :: Web Environment
Classifier: Framework :: Django
Classifier: Intended Audience :: Developers
Classifier: License :: OSI Approved :: BSD License
Classifier: License :: OSI Approved :: MIT License
Classifier: Natural Language :: English
Classifier: Programming Language :: Python
Classifier: Programming Language :: Python :: 3
Classifier: Programming Language :: Python :: 3.5
Classifier: Programming Language :: Python :: 3.6
Classifier: Programming Language :: Python :: 3.7
Classifier: Programming Language :: Python :: 3.8
Classifier: Programming Language :: Python :: 3.9
Requires-Dist: django (>=2.2)
Project-URL: Repository, https://github.com/ellmetha/django-js-routes
